classification_model/VERSION
classification_model/__init__.py
classification_model/config.yml
classification_model/pipeline.py
classification_model/predict.py
classification_model/train_pipeline.py
classification_model/config/__init__.py
classification_model/config/core.py
classification_model/datasets/__init__.py
classification_model/datasets/df_test.csv
classification_model/datasets/df_train.csv
classification_model/processing/__init__.py
classification_model/processing/data_manager.py
classification_model/processing/validation.py
classification_model/trained_models/__init__.py
classification_model/trained_models/classification_model_output_v0.0.1.pkl
nba_betting_model-0.0.1.dist-info/METADATA
nba_betting_model-0.0.1.dist-info/WHEEL
nba_betting_model-0.0.1.dist-info/top_level.txt
nba_betting_model-0.0.1.dist-info/RECORD
